<?xml version="1.0" encoding="UTF-8"?>
<data translate="true">
  <menuitem id="fleet.menu" sequence="98" name="Fleet">
    <menuitem id="fleet.menu.vehicles" name="Vehicles">
      <menuitem id="fleet.menu.vehicle" name="Vehicles" action="action.fleet.view.vehicle" />
      <menuitem id="fleet.menu.odometer" name="Odometer Log" action="action.fleet.view.odometer" />
      <menuitem id="fleet.menu.vehicle.fuel.log" name="Fuel Log" action="action.fleet.view.vehicle.fuel.log" />
      <menuitem id="fleet.menu.maintenance" name="Maintenance" action="action.fleet.view.maintenance" />
      <menuitem id="fleet.menu.traffic.ticket" name="Traffic Ticket" action="action.fleet.view.traffic.ticket" />
    </menuitem>
    <menuitem id="fleet.menu.reports" name="Reports">
      <menuitem id="fleet.menu.reports.odometer" name="Departures Listing" action="action.fleet.report.odometer"/>
    </menuitem>
    <menuitem id="fleet.menu.config" name="Configuration">
      <menuitem id="fleet.menu.config.driver" name="Drivers" action="action.fleet.view.driver" />
      <menuitem id="fleet.menu.config.contract" name="Contracts" action="action.fleet.view.contract" />
      <menuitem id="fleet.menu.config.vehicle.make" name="Make of Vehicle" action="action.fleet.view.vehicle.make" />
      <menuitem id="fleet.menu.config.vehicle.model" name="Model of Vehicle" action="action.fleet.view.vehicle.model" />
      <menuitem id="fleet.menu.config.route" name="Routes" action="action.fleet.view.route" />
    </menuitem>
  </menuitem>
</data>